ghahreman/__init__.py
ghahreman/trophy.py
ghahreman-0.1.0.dist-info/licenses/LICENSE
tests/__init__.py
tests/test_hero.py
ghahreman-0.1.0.dist-info/METADATA
ghahreman-0.1.0.dist-info/WHEEL
ghahreman-0.1.0.dist-info/entry_points.txt
ghahreman-0.1.0.dist-info/top_level.txt
ghahreman-0.1.0.dist-info/RECORD
