Metadata-Version: 2.4
Name: ghahreman
Version: 0.1.0
Summary: A PyVista-based 3D trophy visualization tool
Home-page: https://github.com/Elmino-19/ghahreman
Author: Erfan
Author-email: zelzeleh.19@gmail.com
Classifier: Programming Language :: Python :: 3
Classifier: License :: OSI Approved :: MIT License
Classifier: Operating System :: OS Independent
Requires-Python: >=3.6
License-File: LICENSE
Requires-Dist: pyvista>=0.34.0
Requires-Dist: numpy>=1.20.0
Dynamic: author
Dynamic: author-email
Dynamic: classifier
Dynamic: description
Dynamic: description-content-type
Dynamic: home-page
Dynamic: license-file
Dynamic: requires-dist
Dynamic: requires-python
Dynamic: summary
